nasdaq_protocols/__init__.py
nasdaq_protocols/asn1_app/__init__.py
nasdaq_protocols/asn1_app/codegen.py
nasdaq_protocols/asn1_app/core.py
nasdaq_protocols/asn1_app/soup_session.py
nasdaq_protocols/asn1_app/templates/__init__.py
nasdaq_protocols/asn1_app/templates/ans1_soup_app.mustache
nasdaq_protocols/asn1_app/templates/init.mustache
nasdaq_protocols/common/__init__.py
nasdaq_protocols/common/message_queue.py
nasdaq_protocols/common/session.py
nasdaq_protocols/common/sync_executor.py
nasdaq_protocols/common/types.py
nasdaq_protocols/common/utils.py
nasdaq_protocols/common/message/__init__.py
nasdaq_protocols/common/message/codegen.py
nasdaq_protocols/common/message/parser.py
nasdaq_protocols/common/message/structures.py
nasdaq_protocols/common/message/types.py
nasdaq_protocols/common/message/templates/__init__.py
nasdaq_protocols/common/message/templates/enum.mustache
nasdaq_protocols/common/message/templates/init.mustache
nasdaq_protocols/common/message/templates/message_soup_app.mustache
nasdaq_protocols/common/message/templates/record.mustache
nasdaq_protocols/fix/__init__.py
nasdaq_protocols/fix/_reader.py
nasdaq_protocols/fix/codegen.py
nasdaq_protocols/fix/core.py
nasdaq_protocols/fix/session.py
nasdaq_protocols/fix/types.py
nasdaq_protocols/fix/parser/__init__.py
nasdaq_protocols/fix/parser/definitions.py
nasdaq_protocols/fix/parser/generator.py
nasdaq_protocols/fix/parser/parser.py
nasdaq_protocols/fix/parser/version_types.py
nasdaq_protocols/fix/parser/templates/__init__.py
nasdaq_protocols/fix/parser/templates/app.mustache
nasdaq_protocols/fix/parser/templates/bodies.mustache
nasdaq_protocols/fix/parser/templates/fields.mustache
nasdaq_protocols/fix/parser/templates/groups.mustache
nasdaq_protocols/fix/parser/templates/init.mustache
nasdaq_protocols/fix/parser/templates/messages.mustache
nasdaq_protocols/itch/__init__.py
nasdaq_protocols/itch/codegen.py
nasdaq_protocols/itch/core.py
nasdaq_protocols/itch/session.py
nasdaq_protocols/ouch/__init__.py
nasdaq_protocols-1.2.4.dist-info/licenses/docs/LICENSE.rst
nasdaq_protocols-1.2.4.dist-info/METADATA
nasdaq_protocols-1.2.4.dist-info/WHEEL
nasdaq_protocols-1.2.4.dist-info/entry_points.txt
nasdaq_protocols-1.2.4.dist-info/top_level.txt
nasdaq_protocols-1.2.4.dist-info/RECORD
