Metadata-Version: 2.4
Name: nasdaq-protocols
Version: 1.2.4
Summary: Nasdaq protocols python library
Classifier: Development Status :: 3 - Alpha
Classifier: Topic :: Software Development :: Libraries :: Python Modules
Requires-Python: >=3.10
License-File: docs/LICENSE.rst
Requires-Dist: attrs>=23.1
Requires-Dist: chevron>=0.14.0
Requires-Dist: click>=8.1
Requires-Dist: asn1>=2.6
Requires-Dist: asn1tools==0.164.0
Dynamic: license-file
